qal/__init__.py
qal/autoquery.py
qal/digital_library.py
qal/exceptions.py
qal/ieeexplore.py
qal/main.py
qal/results_store.py
qal/science_direct.py
qal/springer.py
qal/types.py
qal_swflint-1.0.0.data/scripts/qal-auto
qal_swflint-1.0.0.data/scripts/qal-query
qal_swflint-1.0.0.dist-info/LICENSE.txt
qal_swflint-1.0.0.dist-info/METADATA
qal_swflint-1.0.0.dist-info/WHEEL
qal_swflint-1.0.0.dist-info/top_level.txt
qal_swflint-1.0.0.dist-info/RECORD
