Metadata-Version: 2.1
Name: qal-swflint
Version: 1.0.0
Summary: A tool for systematically querying various academic publishing databases.
Home-page: https://github.com/swflint/qal
Author: Samuel W. Flint
Author-email: swflint@flintfam.org
License: MIT
Download-URL: https://github.com/swflint/qal/archive/v1.0.0.tar.gz
Keywords: LITERATURE REVIEW,ACADEMIC,BIBLIOGRAPHY
Platform: UNKNOWN
Classifier: Development Status :: 4 - Beta
Classifier: License :: OSI Approved :: MIT License
Classifier: Programming Language :: Python :: 3
Classifier: Programming Language :: Python :: 3.7
Classifier: Programming Language :: Python :: 3.8
Classifier: Programming Language :: Python :: 3.9
Requires-Dist: requests
Requires-Dist: backoff
Requires-Dist: urllib3
Requires-Dist: jsonpickle
Requires-Dist: tqdm
